LICENSE.txt
README.md
setup.cfg
setup.py
noCheck/__init__.py
noCheck/noCheck.py
noCheck.egg-info/PKG-INFO
noCheck.egg-info/SOURCES.txt
noCheck.egg-info/dependency_links.txt
noCheck.egg-info/not-zip-safe
noCheck.egg-info/top_level.txt