Metadata-Version: 2.1
Name: noCheck
Version: 0.3
Summary: Find highest of two numbers
Home-page: UNKNOWN
Author: Zubair Mushtaq
Author-email: zubair.mushtaq000@gmail.com
License: UNKNOWN
Platform: UNKNOWN
License-File: LICENSE.txt
